{"type":"FeatureCollection","crs":{"type":"name","properties":{"name":"EPSG:4326"}},"features":[{"type":"Feature","id":1,"geometry":{"type":"Point","coordinates":[-34.627778000354397,-77.873888999877408]},"properties":{"OBJECTID":1,"Record_ID_":4,"English_Na":"Belgrano II","Official_N":"Base Antartica Belgrano II","Operator__":"Argentina","Operator_1":" ","Type":"Station","Seasonalit":"Year-Round","Status":"Open","Year_Estab":1979,"Antarctic":"East Antarctica","Latitude__":-77.873889000000005,"Longitude":-34.627777999999999,"Latitude_1":"77° 52.4333' S","Longitud_1":"34° 37.6667' W","Elevation":"256.5","Elevatio_1":"MSL","Peak_Popul":0,"Photo_URL":"https://pgc.quickbase.com/up/bibrbwkpg/a/r4/e56/v0/Base_Belgrano.jpg","Webcam_URL":" ","Date_Modif":null}},{"type":"Feature","id":2,"geometry":{"type":"Point","coordinates":[-62.870451999959812,-64.895370000225284]},"properties":{"OBJECTID":2,"Record_ID_":5,"English_Na":"Brown","Official_N":"Base Antartica Almirante Brown","Operator__":"Argentina","Operator_1":" ","Type":"Station","Seasonalit":"Seasonal","Status":"Open","Year_Estab":1951,"Antarctic":"Antarctic Peninsula","Latitude__":-64.89537,"Longitude":-62.870452,"Latitude_1":"64° 53.7222' S","Longitud_1":"62° 52.2271' W","Elevation":"22","Elevatio_1":"MSL","Peak_Popul":12,"Photo_URL":"https://pgc.quickbase.com/up/bibrbwkpg/a/r5/e56/v0/Base_Brown_Argentina_Puerto_Paraiso.jpg","Webcam_URL":" ","Date_Modif":null}},{"type":"Feature","id":3,"geometry":{"type":"Point","coordinates":[-59.919343999725754,-62.593857999846762]},"properties":{"OBJECTID":3,"Record_ID_":6,"English_Na":"Camara","Official_N":"Base Antartica Camara","Operator__":"Argentina","Operator_1":" ","Type":"Station","Seasonalit":"Seasonal","Status":"Open","Year_Estab":1953,"Antarctic":"Antarctic Peninsula","Latitude__":-62.593857999999997,"Longitude":-59.919344000000002,"Latitude_1":"62° 35.6315' S","Longitud_1":"59° 55.1606' W","Elevation":"22","Elevatio_1":"MSL","Peak_Popul":22,"Photo_URL":"https://pgc.quickbase.com/up/bibrbwkpg/a/r6/e56/v0/C%C3%A1mara-Base.jpg","Webcam_URL":" ","Date_Modif":null}},{"type":"Feature","id":4,"geometry":{"type":"Point","coordinates":[-58.666842000158113,-62.237900000084892]},"properties":{"OBJECTID":4,"Record_ID_":9,"English_Na":"Carlini","Official_N":"Base Antartica Carlini","Operator__":"Argentina","Operator_1":" ","Type":"Station","Seasonalit":"Year-Round","Status":"Open","Year_Estab":1953,"Antarctic":"Antarctic Peninsula","Latitude__":-62.237900000000003,"Longitude":-58.666842000000003,"Latitude_1":"62° 14.274' S","Longitud_1":"58° 40.0105' W","Elevation":"10","Elevatio_1":"MSL","Peak_Popul":80,"Photo_URL":"https://pgc.quickbase.com/up/bibrbwkpg/a/r9/e56/v0/cav2016_carlini.jpg","Webcam_URL":" ","Date_Modif":null}},{"type":"Feature","id":5,"geometry":{"type":"Point","coordinates":[-60.700694999674454,-62.97676000017384]},"properties":{"OBJECTID":5,"Record_ID_":7,"English_Na":"Decepcion","Official_N":"Base Antartica Decepcion","Operator__":"Argentina","Operator_1":" ","Type":"Station","Seasonalit":"Seasonal","Status":"Open","Year_Estab":1948,"Antarctic":"Antarctic Peninsula","Latitude__":-62.976759999999999,"Longitude":-60.700695000000003,"Latitude_1":"62° 58.6056' S","Longitud_1":"60° 42.0417' W","Elevation":"7","Elevatio_1":"MSL","Peak_Popul":36,"Photo_URL":"https://pgc.quickbase.com/up/bibrbwkpg/a/r7/e56/v0/Decepci%BEn_beach_20-01-16.jpg","Webcam_URL":" ","Date_Modif":1588636800000}},{"type":"Feature","id":6,"geometry":{"type":"Point","coordinates":[-56.998054000391789,-63.396959000057791]},"properties":{"OBJECTID":6,"Record_ID_":8,"English_Na":"Esperanza","Official_N":"Base Antartica Esperanza","Operator__":"Argentina","Operator_1":" ","Type":"Station","Seasonalit":"Year-Round","Status":"Open","Year_Estab":1952,"Antarctic":"Antarctic Peninsula","Latitude__":-63.396959000000003,"Longitude":-56.998054000000003,"Latitude_1":"63° 23.8175' S","Longitud_1":"56° 59.8832' W","Elevation":"25","Elevatio_1":"MSL","Peak_Popul":90,"Photo_URL":"https://pgc.quickbase.com/up/bibrbwkpg/a/r8/e56/v0/antartida_base_esperanza_12.jpg","Webcam_URL":" ","Date_Modif":null}},{"type":"Feature","id":7,"geometry":{"type":"Point","coordinates":[-56.623225000033699,-64.241769000039255]},"properties":{"OBJECTID":7,"Record_ID_":10,"English_Na":"Marambio","Official_N":"Base Antartica Marambio","Operator__":"Argentina","Operator_1":" ","Type":"Station","Seasonalit":"Year-Round","Status":"Open","Year_Estab":1969,"Antarctic":"Antarctic Peninsula","Latitude__":-64.241769000000005,"Longitude":-56.623224999999998,"Latitude_1":"64° 14.5061' S","Longitud_1":"56° 37.3935' W","Elevation":"209.5","Elevatio_1":"MSL","Peak_Popul":165,"Photo_URL":"https://pgc.quickbase.com/up/bibrbwkpg/a/r10/e56/v0/BASE-MARAMBIO-H%C3%89RCULES-C-130-Copy.jpg","Webcam_URL":" ","Date_Modif":null}},{"type":"Feature","id":8,"geometry":{"type":"Point","coordinates":[-60.0709479996504,-64.975864999869827]},"properties":{"OBJECTID":8,"Record_ID_":11,"English_Na":"Matienzo","Official_N":"Base Antartica Matienzo","Operator__":"Argentina","Operator_1":" ","Type":"Station","Seasonalit":"Seasonal","Status":"Open","Year_Estab":1961,"Antarctic":"Antarctic Peninsula","Latitude__":-64.975864999999999,"Longitude":-60.070948000000001,"Latitude_1":"64° 58.5519' S","Longitud_1":"60° 4.2569' W","Elevation":"32","Elevatio_1":"MSL","Peak_Popul":12,"Photo_URL":"https://pgc.quickbase.com/up/bibrbwkpg/a/r11/e56/v0/matienzooverflight.jpg","Webcam_URL":" ","Date_Modif":null}},{"type":"Feature","id":9,"geometry":{"type":"Point","coordinates":[-62.97632900008324,-64.325705000085634]},"properties":{"OBJECTID":9,"Record_ID_":12,"English_Na":"Melchior","Official_N":"Base Antartica Melchior","Operator__":"Argentina","Operator_1":" ","Type":"Station","Seasonalit":"Seasonal","Status":"Open","Year_Estab":1947,"Antarctic":"Antarctic Peninsula","Latitude__":-64.325704999999999,"Longitude":-62.976329,"Latitude_1":"64° 19.5423' S","Longitud_1":"62° 58.5797' W","Elevation":"4","Elevatio_1":"MSL","Peak_Popul":15,"Photo_URL":"https://pgc.quickbase.com/up/bibrbwkpg/a/r12/e56/v0/Base%20Melchior.jpg","Webcam_URL":" ","Date_Modif":null}},{"type":"Feature","id":10,"geometry":{"type":"Point","coordinates":[-44.737386999710225,-60.737591999670997]},"properties":{"OBJECTID":10,"Record_ID_":13,"English_Na":"Orcadas","Official_N":"Base Orcadas","Operator__":"Argentina","Operator_1":" ","Type":"Station","Seasonalit":"Year-Round","Status":"Open","Year_Estab":1904,"Antarctic":" ","Latitude__":-60.737591999999999,"Longitude":-44.737386999999998,"Latitude_1":"60° 44.2555' S","Longitud_1":"44° 44.2432' W","Elevation":"8","Elevatio_1":"MSL","Peak_Popul":65,"Photo_URL":"https://pgc.quickbase.com/up/bibrbwkpg/a/r13/e56/v0/Orcadas.jpg","Webcam_URL":" ","Date_Modif":null}},{"type":"Feature","id":11,"geometry":{"type":"Point","coordinates":[-56.230993000226761,-63.478303000183246]},"properties":{"OBJECTID":11,"Record_ID_":14,"English_Na":"Petrel","Official_N":"Base Petrel","Operator__":"Argentina","Operator_1":" ","Type":"Station","Seasonalit":"Seasonal","Status":"Open","Year_Estab":1952,"Antarctic":"Antarctic Peninsula","Latitude__":-63.478302999999997,"Longitude":-56.230992999999998,"Latitude_1":"63° 28.6982' S","Longitud_1":"56° 13.8596' W","Elevation":"18","Elevatio_1":"MSL","Peak_Popul":45,"Photo_URL":"https://pgc.quickbase.com/up/bibrbwkpg/a/r14/e56/v0/petrel2013.jpg","Webcam_URL":" ","Date_Modif":null}},{"type":"Feature","id":12,"geometry":{"type":"Point","coordinates":[-60.954255999714576,-64.155853999562396]},"properties":{"OBJECTID":12,"Record_ID_":15,"English_Na":"Primavera","Official_N":"Base Primavera","Operator__":"Argentina","Operator_1":" ","Type":"Station","Seasonalit":"Seasonal","Status":"Open","Year_Estab":1977,"Antarctic":"Antarctic Peninsula","Latitude__":-64.155854000000005,"Longitude":-60.954256000000001,"Latitude_1":"64° 9.3512' S","Longitud_1":"60° 57.2554' W","Elevation":"50","Elevatio_1":"MSL","Peak_Popul":18,"Photo_URL":"https://pgc.quickbase.com/up/bibrbwkpg/a/r15/e56/v0/primavera.jpg","Webcam_URL":" ","Date_Modif":null}},{"type":"Feature","id":13,"geometry":{"type":"Point","coordinates":[-67.102931000065553,-68.130300000244802]},"properties":{"OBJECTID":13,"Record_ID_":16,"English_Na":"San Martín","Official_N":"Base San Martín","Operator__":"Argentina","Operator_1":" ","Type":"Station","Seasonalit":"Year-Round","Status":"Open","Year_Estab":1951,"Antarctic":"Antarctic Peninsula","Latitude__":-68.130300000000005,"Longitude":-67.102930999999998,"Latitude_1":"68° 7.818' S","Longitud_1":"67° 6.1759' W","Elevation":"5","Elevatio_1":"MSL","Peak_Popul":21,"Photo_URL":"https://pgc.quickbase.com/up/bibrbwkpg/a/r16/e56/v0/San%20Martin.jpg","Webcam_URL":" ","Date_Modif":null}},{"type":"Feature","id":14,"geometry":{"type":"Point","coordinates":[110.52679200035061,-66.282343000129288]},"properties":{"OBJECTID":14,"Record_ID_":19,"English_Na":"Casey","Official_N":"Casey Station","Operator__":"Australia","Operator_1":" ","Type":"Station","Seasonalit":"Year-Round","Status":"Open","Year_Estab":1969,"Antarctic":"East Antarctica","Latitude__":-66.282342999999997,"Longitude":110.526792,"Latitude_1":"66° 16.9406' S","Longitud_1":"110° 31.6075' E","Elevation":"32","Elevatio_1":"MSL","Peak_Popul":120,"Photo_URL":"https://pgc.quickbase.com/up/bibrbwkpg/a/r19/e56/v0/Casey%20from%20air%20006.jpg","Webcam_URL":"http://www.antarctica.gov.au/webcams/casey","Date_Modif":1586044800000}},{"type":"Feature","id":15,"geometry":{"type":"Point","coordinates":[77.969515999663713,-68.575937999638938]},"properties":{"OBJECTID":15,"Record_ID_":20,"English_Na":"Davis","Official_N":"Davis Station","Operator__":"Australia","Operator_1":" ","Type":"Station","Seasonalit":"Year-Round","Status":"Open","Year_Estab":1957,"Antarctic":"East Antarctica","Latitude__":-68.575937999999994,"Longitude":77.969515999999999,"Latitude_1":"68° 34.5563' S","Longitud_1":"77° 58.171' E","Elevation":"27","Elevatio_1":"MSL","Peak_Popul":91,"Photo_URL":"https://pgc.quickbase.com/up/bibrbwkpg/a/r20/e56/v0/Davis%20Aerial%202014005.jpg","Webcam_URL":"http://www.antarctica.gov.au/webcams/davis","Date_Modif":1586044800000}},{"type":"Feature","id":16,"geometry":{"type":"Point","coordinates":[100.60421299963031,-66.249935000299956]},"properties":{"OBJECTID":16,"Record_ID_":17,"English_Na":"Edgeworth David","Official_N":"Edgeworth David Camp","Operator__":"Australia","Operator_1":" ","Type":"Camp","Seasonalit":"Seasonal","Status":"Open","Year_Estab":0,"Antarctic":"East Antarctica","Latitude__":-66.249934999999994,"Longitude":100.604213,"Latitude_1":"66° 14.9961' S","Longitud_1":"100° 36.2528' E","Elevation":"15","Elevatio_1":"MSL","Peak_Popul":0,"Photo_URL":"https://pgc.quickbase.com/up/bibrbwkpg/a/r17/e56/v0/Bunger%20Crosswind%20Strip.png","Webcam_URL":" ","Date_Modif":null}},{"type":"Feature","id":17,"geometry":{"type":"Point","coordinates":[76.38069600042013,-69.388295999560683]},"properties":{"OBJECTID":17,"Record_ID_":22,"English_Na":"Law","Official_N":"Law Station","Operator__":"Australia","Operator_1":" ","Type":"Refuge","Seasonalit":"Seasonal","Status":"Open","Year_Estab":0,"Antarctic":"East Antarctica","Latitude__":-69.388295999999997,"Longitude":76.380696,"Latitude_1":"69° 23.2978' S","Longitud_1":"76° 22.8418' E","Elevation":"65","Elevatio_1":"MSL","Peak_Popul":13,"Photo_URL":"https://pgc.quickbase.com/up/bibrbwkpg/a/r22/e56/v0/Law%20Base.png","Webcam_URL":" ","Date_Modif":null}},{"type":"Feature","id":18,"geometry":{"type":"Point","coordinates":[62.873028000242073,-67.60264400022038]},"properties":{"OBJECTID":18,"Record_ID_":21,"English_Na":"Mawson","Official_N":"Mawson Station","Operator__":"Australia","Operator_1":" ","Type":"Station","Seasonalit":"Year-Round","Status":"Open","Year_Estab":1954,"Antarctic":"East Antarctica","Latitude__":-67.602643999999998,"Longitude":62.873027999999998,"Latitude_1":"67° 36.1586' S","Longitud_1":"62° 52.3817' E","Elevation":"15","Elevatio_1":"MSL","Peak_Popul":53,"Photo_URL":"https://pgc.quickbase.com/up/bibrbwkpg/a/r21/e56/v0/MawsonAirCasa_20050203.jpg","Webcam_URL":"http://www.antarctica.gov.au/webcams/mawson","Date_Modif":1586044800000}},{"type":"Feature","id":19,"geometry":{"type":"Point","coordinates":[111.48335199969512,-66.689393999833214]},"properties":{"OBJECTID":19,"Record_ID_":18,"English_Na":"Wilkins Aerodrome","Official_N":"Wilkins Aerodrome","Operator__":"Australia","Operator_1":" ","Type":"Airfield Camp","Seasonalit":"Seasonal","Status":"Temporarily Closed","Year_Estab":2003,"Antarctic":"East Antarctica","Latitude__":-66.689393999999993,"Longitude":111.483352,"Latitude_1":"66° 41.3636' S","Longitud_1":"111° 29.0011' E","Elevation":"740","Elevatio_1":"MSL","Peak_Popul":12,"Photo_URL":"https://pgc.quickbase.com/up/bibrbwkpg/a/r18/e56/v0/Wilkins%20Camp%20-%20Laydown%20Area%20%26%20Apron.jpg","Webcam_URL":" ","Date_Modif":null}},{"type":"Feature","id":20,"geometry":{"type":"Point","coordinates":[23.346890999819834,-71.949857999746825]},"properties":{"OBJECTID":20,"Record_ID_":23,"English_Na":"Princess Elisabeth Antarctica","Official_N":"Princess Elisabeth Antarctica","Operator__":"Belgium","Operator_1":" ","Type":"Station","Seasonalit":"Seasonal","Status":"Open","Year_Estab":2008,"Antarctic":"Dronning Maud Land","Latitude__":-71.949858000000006,"Longitude":23.346890999999999,"Latitude_1":"71° 56.9915' S","Longitud_1":"23° 20.8135' E","Elevation":"1,382","Elevatio_1":"MSL","Peak_Popul":50,"Photo_URL":"https://pgc.quickbase.com/up/bibrbwkpg/a/r23/e56/v0/PEA_station_AntarctiQ_16-02-14(2).JPG","Webcam_URL":" ","Date_Modif":null}},{"type":"Feature","id":21,"geometry":{"type":"Point","coordinates":[-58.398721999620534,-62.085471999932793]},"properties":{"OBJECTID":21,"Record_ID_":24,"English_Na":"Comandante Ferraz","Official_N":"Estacao Antartica Comandante Ferraz","Operator__":"Brazil","Operator_1":" ","Type":"Station","Seasonalit":"Year-Round","Status":"Open","Year_Estab":1984,"Antarctic":"Antarctic Peninsula","Latitude__":-62.085472000000003,"Longitude":-58.398721999999999,"Latitude_1":"62° 5.1283' S","Longitud_1":"58° 23.9233' W","Elevation":"3","Elevatio_1":"Other","Peak_Popul":64,"Photo_URL":"https://pgc.quickbase.com/up/bibrbwkpg/a/r24/e56/v0/EACF%20frente%201.jpg","Webcam_URL":" ","Date_Modif":null}},{"type":"Feature","id":22,"geometry":{"type":"Point","coordinates":[-60.365233839869802,-62.640723070113552]},"properties":{"OBJECTID":22,"Record_ID_":25,"English_Na":"St. Kliment Ohridski","Official_N":"St. Kliment Ohridski Base","Operator__":"Bulgaria","Operator_1":" ","Type":"Station","Seasonalit":"Seasonal","Status":"Open","Year_Estab":1988,"Antarctic":"Antarctic Peninsula","Latitude__":-62.64072307,"Longitude":-60.365233840000002,"Latitude_1":"62° 38.4434' S","Longitud_1":"60° 21.914' W","Elevation":"15","Elevatio_1":"MSL","Peak_Popul":22,"Photo_URL":"https://pgc.quickbase.com/up/bibrbwkpg/a/r25/e56/v0/Bulgarian%20Antarctic%20Base%20(4)_Christo%20Pimpirev_27.01.2011.JPG","Webcam_URL":" ","Date_Modif":1575849600000}},{"type":"Feature","id":23,"geometry":{"type":"Point","coordinates":[-59.663602999878492,-62.478716999689766]},"properties":{"OBJECTID":23,"Record_ID_":28,"English_Na":"Arturo Prat Antarctic Naval Base","Official_N":"Base Naval Antartica Arturo Prat","Operator__":"Chile","Operator_1":" ","Type":"Station","Seasonalit":"Year-Round","Status":"Open","Year_Estab":1947,"Antarctic":"Antarctic Peninsula","Latitude__":-62.478717000000003,"Longitude":-59.663603000000002,"Latitude_1":"62° 28.723' S","Longitud_1":"59° 39.8162' W","Elevation":"3","Elevatio_1":"MSL","Peak_Popul":32,"Photo_URL":"https://pgc.quickbase.com/up/bibrbwkpg/a/r28/e56/v0/Base%20Prat.jpg","Webcam_URL":" ","Date_Modif":1575849600000}},{"type":"Feature","id":24,"geometry":{"type":"Point","coordinates":[-58.961149999672728,-62.201521999740464]},"properties":{"OBJECTID":24,"Record_ID_":229,"English_Na":"Bahía Fildes Maritime Station","Official_N":"Estacion Marítima Bahía Fildes","Operator__":"Chile","Operator_1":" ","Type":"Station","Seasonalit":"Year-Round","Status":"Open","Year_Estab":0,"Antarctic":" ","Latitude__":-62.201521999999997,"Longitude":-58.961150000000004,"Latitude_1":"62° 12.0913' S","Longitud_1":"58° 57.669' W","Elevation":" ","Elevatio_1":" ","Peak_Popul":0,"Photo_URL":"https://pgc.quickbase.com/up/bibrbwkpg/a/r229/e56/v0/Bah%C3%ADa%20Fildes%20Maritime%20Station.jpg","Webcam_URL":" ","Date_Modif":null}},{"type":"Feature","id":25,"geometry":{"type":"Point","coordinates":[-68.91481500041192,-67.761321999910308]},"properties":{"OBJECTID":25,"Record_ID_":102,"English_Na":"Carvajal","Official_N":"Lieutenant Luis Carvajal Villarroel (SCTJ)","Operator__":"Chile","Operator_1":" ","Type":"Station","Seasonalit":"Seasonal","Status":"Temporarily Closed","Year_Estab":1985,"Antarctic":"Antarctic Peninsula","Latitude__":-67.761322000000007,"Longitude":-68.914815000000004,"Latitude_1":"67° 45.6793' S","Longitud_1":"68° 54.8889' W","Elevation":"92","Elevatio_1":"MSL","Peak_Popul":46,"Photo_URL":"https://pgc.quickbase.com/up/bibrbwkpg/a/r102/e56/v0/carvajal%2002_Instituto%20Ant%E1rtico%20Chileno.JPG","Webcam_URL":" ","Date_Modif":1491955200000}},{"type":"Feature","id":26,"geometry":{"type":"Point","coordinates":[-60.77117799986479,-62.470150000322235]},"properties":{"OBJECTID":26,"Record_ID_":32,"English_Na":"Dr. Guillermo Mann","Official_N":"Base Dr. Guillermo Mann","Operator__":"Chile","Operator_1":" ","Type":"Station","Seasonalit":"Seasonal","Status":"Open","Year_Estab":1991,"Antarctic":"Antarctic Peninsula","Latitude__":-62.470149999999997,"Longitude":-60.771177999999999,"Latitude_1":"62° 28.209' S","Longitud_1":"60° 46.2707' W","Elevation":"15","Elevatio_1":"MSL","Peak_Popul":8,"Photo_URL":"https://pgc.quickbase.com/up/bibrbwkpg/a/r32/e56/v0/SAM_0528.JPG","Webcam_URL":" ","Date_Modif":1489104000000}},{"type":"Feature","id":27,"geometry":{"type":"Point","coordinates":[-82.916667000281791,-79.766667000281814]},"properties":{"OBJECTID":27,"Record_ID_":225,"English_Na":"Estacion Polar Científica Conjunta Glaciar Union","Official_N":"Estacion Polar Científica Conjunta Glaciar Union (EPCCGU)","Operator__":"Chile","Operator_1":" ","Type":"Camp","Seasonalit":"Seasonal","Status":"Open","Year_Estab":0,"Antarctic":"West Antarctica","Latitude__":-79.766666999999998,"Longitude":-82.916667000000004,"Latitude_1":"79° 46' S","Longitud_1":"82° 55' W","Elevation":"680","Elevatio_1":"MSL","Peak_Popul":0,"Photo_URL":"https://pgc.quickbase.com/up/bibrbwkpg/a/r225/e56/v0/Union%20Glacier_Instituto%20Ant%E1rtico%20Chileno.jpg","Webcam_URL":" ","Date_Modif":1588636800000}},{"type":"Feature","id":28,"geometry":{"type":"Point","coordinates":[-62.857498999778954,-64.82386200043095]},"properties":{"OBJECTID":28,"Record_ID_":34,"English_Na":"Gabriel Gonzalez Videla","Official_N":"Base Antartica Presidente Gabriel Gonzalez Videla","Operator__":"Chile","Operator_1":" ","Type":"Station","Seasonalit":"Seasonal","Status":"Open","Year_Estab":1951,"Antarctic":"Antarctic Peninsula","Latitude__":-64.823862000000005,"Longitude":-62.857498999999997,"Latitude_1":"64° 49.4317' S","Longitud_1":"62° 51.4499' W","Elevation":"6","Elevatio_1":"MSL","Peak_Popul":15,"Photo_URL":"https://pgc.quickbase.com/up/bibrbwkpg/a/r34/e56/v0/base-ggv.jpg","Webcam_URL":" ","Date_Modif":null}},{"type":"Feature","id":29,"geometry":{"type":"Point","coordinates":[-58.980605000220521,-62.193794000392757]},"properties":{"OBJECTID":29,"Record_ID_":27,"English_Na":"Lieutenant Rodolfo Marsh Martin Aerodrome","Official_N":"Aerodromo Teniente Rodolfo Marsh Martin","Operator__":"Chile","Operator_1":" ","Type":"Airfield Camp","Seasonalit":"Year-Round","Status":"Open","Year_Estab":1980,"Antarctic":"Antarctic Peninsula","Latitude__":-62.193793999999997,"Longitude":-58.980604999999997,"Latitude_1":"62° 11.6276' S","Longitud_1":"58° 58.8363' W","Elevation":"46","Elevatio_1":"MSL","Peak_Popul":15,"Photo_URL":"https://pgc.quickbase.com/up/bibrbwkpg/a/r27/e56/v0/Foto%20N%C2%BA%2002%20Base%20Frei%2C%20vista%20a%C3%A9rea%20Aer%C3%B3dromo%20Tte.%20Marsh%2C%20Base%20Pdte.%20Frei.jpg","Webcam_URL":" ","Date_Modif":1491955200000}},{"type":"Feature","id":30,"geometry":{"type":"Point","coordinates":[-57.899780999993141,-63.320950999588945]},"properties":{"OBJECTID":30,"Record_ID_":31,"English_Na":"O'Higgins Base","Official_N":"General Bernardo O'Higgins Riquelme","Operator__":"Chile","Operator_1":" ","Type":"Station","Seasonalit":"Year-Round","Status":"Open","Year_Estab":1948,"Antarctic":"Antarctic Peninsula","Latitude__":-63.320951000000001,"Longitude":-57.899780999999997,"Latitude_1":"63° 19.2571' S","Longitud_1":"57° 53.9869' W","Elevation":"12","Elevatio_1":"MSL","Peak_Popul":60,"Photo_URL":"https://pgc.quickbase.com/up/bibrbwkpg/a/r31/e56/v0/Base%20O%27Higgins.jpg","Webcam_URL":" ","Date_Modif":1575849600000}},{"type":"Feature","id":31,"geometry":{"type":"Point","coordinates":[-58.962627000335772,-62.20023199960707]},"properties":{"OBJECTID":31,"Record_ID_":30,"English_Na":"President Eduardo Frei Antartctic Base","Official_N":"Base Aerea Antartica Presidente Eduardo Frei Montalva","Operator__":"Chile","Operator_1":" ","Type":"Station","Seasonalit":"Year-Round","Status":"Open","Year_Estab":1969,"Antarctic":"Antarctic Peninsula","Latitude__":-62.200232,"Longitude":-58.962626999999998,"Latitude_1":"62° 12.0139' S","Longitud_1":"58° 57.7576' W","Elevation":"48","Elevatio_1":"MSL","Peak_Popul":150,"Photo_URL":"https://pgc.quickbase.com/up/bibrbwkpg/a/r30/e56/v0/Base%20Frei%20Vista_a%C3%A9rea_congelada%202.jpg","Webcam_URL":" ","Date_Modif":null}},{"type":"Feature","id":32,"geometry":{"type":"Point","coordinates":[-58.962675999897442,-62.201373000063882]},"properties":{"OBJECTID":32,"Record_ID_":29,"English_Na":"Professor Julio Escudero","Official_N":"Profesor Julio Escudero Base","Operator__":"Chile","Operator_1":" ","Type":"Station","Seasonalit":"Seasonal","Status":"Open","Year_Estab":1995,"Antarctic":"Antarctic Peninsula","Latitude__":-62.201372999999997,"Longitude":-58.962676000000002,"Latitude_1":"62° 12.0824' S","Longitud_1":"58° 57.7606' W","Elevation":"10","Elevatio_1":"MSL","Peak_Popul":60,"Photo_URL":"https://pgc.quickbase.com/up/bibrbwkpg/a/r29/e56/v0/P1040293.JPG","Webcam_URL":" ","Date_Modif":null}},{"type":"Feature","id":33,"geometry":{"type":"Point","coordinates":[-57.898224000137475,-63.320657999567004]},"properties":{"OBJECTID":33,"Record_ID_":104,"English_Na":"Rada Covadonga","Official_N":"Rada Covadonga","Operator__":"Chile","Operator_1":" ","Type":"Station","Seasonalit":"Seasonal","Status":"Open","Year_Estab":0,"Antarctic":"Antarctic Peninsula","Latitude__":-63.320658000000002,"Longitude":-57.898223999999999,"Latitude_1":"63° 19.2395' S","Longitud_1":"57° 53.8934' W","Elevation":" ","Elevatio_1":" ","Peak_Popul":0,"Photo_URL":" ","Webcam_URL":" ","Date_Modif":null}},{"type":"Feature","id":34,"geometry":{"type":"Point","coordinates":[-58.9347400003507,-62.21015100016848]},"properties":{"OBJECTID":34,"Record_ID_":103,"English_Na":"Ripamonti","Official_N":"Ripamonti","Operator__":"Chile","Operator_1":" ","Type":"Refuge","Seasonalit":"Seasonal","Status":"Open","Year_Estab":0,"Antarctic":"Antarctic Peninsula","Latitude__":-62.210151000000003,"Longitude":-58.934739999999998,"Latitude_1":"62° 12.6091' S","Longitud_1":"58° 56.0844' W","Elevation":"50","Elevatio_1":"MSL","Peak_Popul":0,"Photo_URL":"https://pgc.quickbase.com/up/bibrbwkpg/a/r103/e56/v0/ripamonti-2_INACH.jpg","Webcam_URL":" ","Date_Modif":1591315200000}},{"type":"Feature","id":35,"geometry":{"type":"Point","coordinates":[-59.700724000312334,-62.378533000397624]},"properties":{"OBJECTID":35,"Record_ID_":33,"English_Na":"Risopatron","Official_N":"Luis Risopatron","Operator__":"Chile","Operator_1":" ","Type":"Station","Seasonalit":"Seasonal","Status":"Open","Year_Estab":1949,"Antarctic":"Antarctic Peninsula","Latitude__":-62.378532999999997,"Longitude":-59.700724000000001,"Latitude_1":"62° 22.712' S","Longitud_1":"59° 42.0434' W","Elevation":"15","Elevatio_1":"MSL","Peak_Popul":6,"Photo_URL":"https://pgc.quickbase.com/up/bibrbwkpg/a/r33/e56/v0/IMG_0610.JPG","Webcam_URL":" ","Date_Modif":null}},{"type":"Feature","id":36,"geometry":{"type":"Point","coordinates":[-63.583806000146751,-64.87585799974687]},"properties":{"OBJECTID":36,"Record_ID_":35,"English_Na":"Yelcho","Official_N":"Base Yelcho","Operator__":"Chile","Operator_1":" ","Type":"Station","Seasonalit":"Seasonal","Status":"Open","Year_Estab":1962,"Antarctic":"Antarctic Peninsula","Latitude__":-64.875857999999994,"Longitude":-63.583806000000003,"Latitude_1":"64° 52.5515' S","Longitud_1":"63° 35.0284' W","Elevation":"10","Elevatio_1":"MSL","Peak_Popul":28,"Photo_URL":"https://pgc.quickbase.com/up/bibrbwkpg/a/r35/e56/v0/DSC02724.JPG","Webcam_URL":" ","Date_Modif":null}},{"type":"Feature","id":37,"geometry":{"type":"Point","coordinates":[-58.9619919998309,-62.217519000001801]},"properties":{"OBJECTID":37,"Record_ID_":73,"English_Na":"Great Wall","Official_N":"Great Wall Station","Operator__":"China","Operator_1":"China","Type":"Station","Seasonalit":"Year-Round","Status":"Open","Year_Estab":1985,"Antarctic":"Antarctic Peninsula","Latitude__":-62.217519000000003,"Longitude":-58.961992000000002,"Latitude_1":"62° 13.0511' S","Longitud_1":"58° 57.7195' W","Elevation":"10","Elevatio_1":"MSL","Peak_Popul":60,"Photo_URL":"https://pgc.quickbase.com/up/bibrbwkpg/a/r73/e56/v0/Great%20Wall_overview%20of%20the%20Station_Cao%20Jianjun_2014-09-25.jpg","Webcam_URL":" ","Date_Modif":null}},{"type":"Feature","id":38,"geometry":{"type":"Point","coordinates":[77.11599730043514,-80.417189720029512]},"properties":{"OBJECTID":38,"Record_ID_":74,"English_Na":"Kunlun","Official_N":"Kunlun Station","Operator__":"China","Operator_1":"China","Type":"Station","Seasonalit":"Seasonal","Status":"Open","Year_Estab":2009,"Antarctic":"East Antarctica","Latitude__":-80.417189719999996,"Longitude":77.115997300000004,"Latitude_1":"80° 25.0314' S","Longitud_1":"77° 6.9598' E","Elevation":"4,087","Elevatio_1":"MSL","Peak_Popul":26,"Photo_URL":"https://pgc.quickbase.com/up/bibrbwkpg/a/r74/e56/v0/Kunlun_overview%20of%20the%20Station_Wei%20Fuhai_2015-01-22.JPG","Webcam_URL":" ","Date_Modif":null}},{"type":"Feature","id":39,"geometry":{"type":"Point","coordinates":[76.966666999782262,-73.849999999800104]},"properties":{"OBJECTID":39,"Record_ID_":96,"English_Na":"Taishan","Official_N":"Taishan","Operator__":"China","Operator_1":"China","Type":"Camp","Seasonalit":"Seasonal","Status":"Open","Year_Estab":2014,"Antarctic":"East Antarctica","Latitude__":-73.849999999999994,"Longitude":76.966667000000001,"Latitude_1":"73° 51' S","Longitud_1":"76° 58' E","Elevation":"2,621","Elevatio_1":"MSL","Peak_Popul":20,"Photo_URL":"https://pgc.quickbase.com/up/bibrbwkpg/a/r96/e56/v0/Taishan_close%20look_Wei%20Fuhai_2014-12-21.JPG","Webcam_URL":" ","Date_Modif":1491782400000}},{"type":"Feature","id":40,"geometry":{"type":"Point","coordinates":[76.371870999946736,-69.373205999757033]},"properties":{"OBJECTID":40,"Record_ID_":75,"English_Na":"Zhongshan","Official_N":"Zhongshan Station","Operator__":"China","Operator_1":"China","Type":"Station","Seasonalit":"Year-Round","Status":"Open","Year_Estab":1989,"Antarctic":"East Antarctica","Latitude__":-69.373205999999996,"Longitude":76.371870999999999,"Latitude_1":"69° 22.3924' S","Longitud_1":"76° 22.3123' E","Elevation":"11","Elevatio_1":"MSL","Peak_Popul":60,"Photo_URL":"https://pgc.quickbase.com/up/bibrbwkpg/a/r75/e56/v0/Zhongshan_overview%20of%20the%20Station%2001_Wei%20Fuhai_2014-02-26.JPG","Webcam_URL":" ","Date_Modif":null}},{"type":"Feature","id":41,"geometry":{"type":"Point","coordinates":[-57.88259199962107,-63.800625000143611]},"properties":{"OBJECTID":41,"Record_ID_":36,"English_Na":"Johann Gregor Mendel","Official_N":"Ceska vedecka stanice Johanna Gregora Mendela","Operator__":"Czech Republic","Operator_1":" ","Type":"Station","Seasonalit":"Seasonal","Status":"Open","Year_Estab":2006,"Antarctic":"Antarctic Peninsula","Latitude__":-63.800624999999997,"Longitude":-57.882592000000002,"Latitude_1":"63° 48.0375' S","Longitud_1":"57° 52.9555' W","Elevation":"10","Elevatio_1":"MSL","Peak_Popul":20,"Photo_URL":"https://pgc.quickbase.com/up/bibrbwkpg/a/r36/e56/v0/Panorama04_Kamil_Laska.jpg","Webcam_URL":" ","Date_Modif":null}},{"type":"Feature","id":42,"geometry":{"type":"Point","coordinates":[-58.983333000117796,-62.249999999600277]},"properties":{"OBJECTID":42,"Record_ID_":236,"English_Na":"Nelson","Official_N":"Eco Nelson Structures","Operator__":"Czech Republic","Operator_1":" ","Type":"Refuge","Seasonalit":"Seasonal","Status":"Open","Year_Estab":0,"Antarctic":"Antarctic Peninsula","Latitude__":-62.25,"Longitude":-58.983333000000002,"Latitude_1":"62° 15' S","Longitud_1":"58° 59' W","Elevation":" ","Elevatio_1":" ","Peak_Popul":12,"Photo_URL":" ","Webcam_URL":" ","Date_Modif":null}},{"type":"Feature","id":43,"geometry":{"type":"Point","coordinates":[-59.740968589928457,-62.44932928032199]},"properties":{"OBJECTID":43,"Record_ID_":38,"English_Na":"Pedro Vicente Maldonado","Official_N":"Pedro Vicente Maldonado Base","Operator__":"Ecuador","Operator_1":" ","Type":"Station","Seasonalit":"Seasonal","Status":"Open","Year_Estab":1990,"Antarctic":"Antarctic Peninsula","Latitude__":-62.449329280000001,"Longitude":-59.740968590000001,"Latitude_1":"62° 26.9598' S","Longitud_1":"59° 44.4581' W","Elevation":"10","Elevatio_1":"MSL","Peak_Popul":34,"Photo_URL":"https://pgc.quickbase.com/up/bibrbwkpg/a/r38/e56/v0/Pedro%20Vicente%20Maldonado.jpg","Webcam_URL":" ","Date_Modif":null}},{"type":"Feature","id":44,"geometry":{"type":"Point","coordinates":[-58.395161199629626,-62.120990180052729]},"properties":{"OBJECTID":44,"Record_ID_":37,"English_Na":"Republica del Ecuador","Official_N":"Refugio República del Ecuador","Operator__":"Ecuador","Operator_1":" ","Type":"Refuge","Seasonalit":"Seasonal","Status":"Open","Year_Estab":1990,"Antarctic":"Antarctic Peninsula","Latitude__":-62.12099018,"Longitude":-58.395161199999997,"Latitude_1":"62° 7.2594' S","Longitud_1":"58° 23.7097' W","Elevation":"10","Elevatio_1":"MSL","Peak_Popul":4,"Photo_URL":"https://pgc.quickbase.com/up/bibrbwkpg/a/r37/e56/v0/FOTO-REFUGIO-17-DIC-2013.jpg","Webcam_URL":" ","Date_Modif":null}},{"type":"Feature","id":45,"geometry":{"type":"Point","coordinates":[-13.407357639743225,-73.042281939559814]},"properties":{"OBJECTID":45,"Record_ID_":39,"English_Na":"Aboa","Official_N":"Aboa Station","Operator__":"Finland","Operator_1":" ","Type":"Station","Seasonalit":"Seasonal","Status":"Open","Year_Estab":1988,"Antarctic":"Dronning Maud Land","Latitude__":-73.042281939999995,"Longitude":-13.407357640000001,"Latitude_1":"73° 2.5369' S","Longitud_1":"13° 24.4415' W","Elevation":"400","Elevatio_1":"MSL","Peak_Popul":17,"Photo_URL":"https://pgc.quickbase.com/up/bibrbwkpg/a/r39/e56/v0/Aboa_station_FINNARP%20(2)_13.1.6.JPG","Webcam_URL":" ","Date_Modif":1544486400000}},{"type":"Feature","id":46,"geometry":{"type":"Point","coordinates":[134.14583300029278,-70.425000000349712]},"properties":{"OBJECTID":46,"Record_ID_":117,"English_Na":"D85 Skiway camp","Official_N":"D85 Skiway camp","Operator__":"France","Operator_1":" ","Type":"Airfield Camp","Seasonalit":"Seasonal","Status":"Open","Year_Estab":0,"Antarctic":"East Antarctica","Latitude__":-70.424999999999997,"Longitude":134.14583300000001,"Latitude_1":"70° 25.5' S","Longitud_1":"134° 8.75' E","Elevation":"2,850","Elevatio_1":"WGS84","Peak_Popul":0,"Photo_URL":" ","Webcam_URL":" ","Date_Modif":null}},{"type":"Feature","id":47,"geometry":{"type":"Point","coordinates":[140.0013330003178,-66.662832999843033]},"properties":{"OBJECTID":47,"Record_ID_":41,"English_Na":"Dumont d'Urville","Official_N":"Dumont d'Urville Station","Operator__":"France","Operator_1":" ","Type":"Station","Seasonalit":"Year-Round","Status":"Open","Year_Estab":1956,"Antarctic":"East Antarctica","Latitude__":-66.662833000000006,"Longitude":140.00133299999999,"Latitude_1":"66° 39.77' S","Longitud_1":"140° 0.08' E","Elevation":"42","Elevatio_1":"WGS84","Peak_Popul":90,"Photo_URL":"https://pgc.quickbase.com/up/bibrbwkpg/a/r41/e56/v0/Ant-DDU-Station-Infrapol-2016-red.jpg","Webcam_URL":" ","Date_Modif":null}},{"type":"Feature","id":48,"geometry":{"type":"Point","coordinates":[139.90716999989559,-66.687608000209025]},"properties":{"OBJECTID":48,"Record_ID_":40,"English_Na":"Robert Guillard","Official_N":"Robert Guillard","Operator__":"France","Operator_1":"Italy","Type":"Station","Seasonalit":"Seasonal","Status":"Open","Year_Estab":1994,"Antarctic":"East Antarctica","Latitude__":-66.687607999999997,"Longitude":139.90717000000001,"Latitude_1":"66° 41.2565' S","Longitud_1":"139° 54.4302' E","Elevation":"10","Elevatio_1":"WGS84","Peak_Popul":20,"Photo_URL":"https://pgc.quickbase.com/up/bibrbwkpg/a/r40/e56/v0/Prudhomme_Elements%20de%20traverse_Katell%20PIERRE_06-02-16.JPG","Webcam_URL":" ","Date_Modif":1505001600000}},{"type":"Feature","id":49,"geometry":{"type":"Point","coordinates":[-58.666715999743531,-62.237609000155203]},"properties":{"OBJECTID":49,"Record_ID_":43,"English_Na":"Dallmann","Official_N":"Dallmann Laboratory at Carlini","Operator__":"Germany","Operator_1":"Argentina","Type":"Laboratory","Seasonalit":"Seasonal","Status":"Open","Year_Estab":1994,"Antarctic":"Antarctic Peninsula","Latitude__":-62.237608999999999,"Longitude":-58.666716000000001,"Latitude_1":"62° 14.2565' S","Longitud_1":"58° 40.003' W","Elevation":"10","Elevatio_1":"WGS84","Peak_Popul":16,"Photo_URL":"https://pgc.quickbase.com/up/bibrbwkpg/a/r43/e56/v0/Dallmann_building_AWI_06-12-23.jpg","Webcam_URL":" ","Date_Modif":null}},{"type":"Feature","id":50,"geometry":{"type":"Point","coordinates":[-57.900940000380672,-63.321091999795897]},"properties":{"OBJECTID":50,"Record_ID_":44,"English_Na":"German Antarctic Receiving Station (GARS)","Official_N":"German Antarctic Receiving Station (GARS)","Operator__":"Germany","Operator_1":"Germany","Type":"Station","Seasonalit":"Year-Round","Status":"Open","Year_Estab":1991,"Antarctic":"Antarctic Peninsula","Latitude__":-63.321092,"Longitude":-57.900939999999999,"Latitude_1":"63° 19.2655' S","Longitud_1":"57° 54.0564' W","Elevation":"17","Elevatio_1":"WGS84","Peak_Popul":10,"Photo_URL":"https://pgc.quickbase.com/up/bibrbwkpg/a/r44/e56/v0/O_Higgins_Wendlant_2048.jpg","Webcam_URL":" ","Date_Modif":1549670400000}},{"type":"Feature","id":51,"geometry":{"type":"Point","coordinates":[164.22121500007222,-74.635500999571434]},"properties":{"OBJECTID":51,"Record_ID_":45,"English_Na":"Gondwana","Official_N":"Gondwana Station","Operator__":"Germany","Operator_1":" ","Type":"Station","Seasonalit":"Seasonal","Status":"Open","Year_Estab":1983,"Antarctic":"Transantarctic Mountains","Latitude__":-74.635501000000005,"Longitude":164.221215,"Latitude_1":"74° 38.1301' S","Longitud_1":"164° 13.2729' E","Elevation":"20","Elevatio_1":"WGS84","Peak_Popul":20,"Photo_URL":"https://pgc.quickbase.com/up/bibrbwkpg/a/r45/e56/v0/pol_gondwana_station_foto_k_en.jpg","Webcam_URL":" ","Date_Modif":null}},{"type":"Feature","id":52,"geometry":{"type":"Point","coordinates":[0.066335999706666371,-75.001909000100227]},"properties":{"OBJECTID":52,"Record_ID_":46,"English_Na":"Kohnen","Official_N":"Kohnen Station","Operator__":"Germany","Operator_1":" ","Type":"Station","Seasonalit":"Seasonal","Status":"Temporarily Closed","Year_Estab":2000,"Antarctic":"Dronning Maud Land","Latitude__":-75.001908999999998,"Longitude":0.066336000000000006,"Latitude_1":"75° 0.1145' S","Longitud_1":"0° 3.9802' E","Elevation":"2,892","Elevatio_1":"WGS84","Peak_Popul":28,"Photo_URL":"https://pgc.quickbase.com/up/bibrbwkpg/a/r46/e56/v0/csm_20130112_CoFiKohnen2012-13_Kohnen2012_MLeonhardt_94aa025d13.jpg","Webcam_URL":" ","Date_Modif":null}},{"type":"Feature","id":53,"geometry":{"type":"Point","coordinates":[-8.2796380002934598,-70.666626000389556]},"properties":{"OBJECTID":53,"Record_ID_":47,"English_Na":"Neumayer III","Official_N":"Neumayer-Station III","Operator__":"Germany","Operator_1":" ","Type":"Station","Seasonalit":"Year-Round","Status":"Open","Year_Estab":2009,"Antarctic":"Dronning Maud Land","Latitude__":-70.666625999999994,"Longitude":-8.2796380000000003,"Latitude_1":"70° 39.9976' S","Longitud_1":"8° 16.7783' W","Elevation":"43","Elevatio_1":"MSL","Peak_Popul":60,"Photo_URL":"https://pgc.quickbase.com/up/bibrbwkpg/a/r47/e56/v0/NMIII_.jpg","Webcam_URL":"http://www.awi.de/en/expedition/stations/neumayer-station-iii.html","Date_Modif":null}},{"type":"Feature","id":54,"geometry":{"type":"Point","coordinates":[76.1952500001874,-69.40680000031972]},"properties":{"OBJECTID":54,"Record_ID_":48,"English_Na":"Bharati","Official_N":"Bharati Station","Operator__":"India","Operator_1":" ","Type":"Station","Seasonalit":"Year-Round","Status":"Open","Year_Estab":2012,"Antarctic":"East Antarctica","Latitude__":-69.406800000000004,"Longitude":76.195250000000001,"Latitude_1":"69° 24.408' S","Longitud_1":"76° 11.715' E","Elevation":"35","Elevatio_1":" ","Peak_Popul":47,"Photo_URL":"https://pgc.quickbase.com/up/bibrbwkpg/a/r48/e56/v0/5N7A3386.jpg","Webcam_URL":" ","Date_Modif":null}},{"type":"Feature","id":55,"geometry":{"type":"Point","coordinates":[11.730782999635778,-70.766833999889172]},"properties":{"OBJECTID":55,"Record_ID_":50,"English_Na":"Maitri","Official_N":"Maitri Station","Operator__":"India","Operator_1":" ","Type":"Station","Seasonalit":"Year-Round","Status":"Open","Year_Estab":1989,"Antarctic":"Dronning Maud Land","Latitude__":-70.766834000000003,"Longitude":11.730783000000001,"Latitude_1":"70° 46.01' S","Longitud_1":"11° 43.847' E","Elevation":"117","Elevatio_1":"MSL","Peak_Popul":65,"Photo_URL":"https://pgc.quickbase.com/up/bibrbwkpg/a/r50/e56/v0/Maitri4_National%20Centre%20for%20Antarctic%20and%20Ocean%20Research.jpg","Webcam_URL":" ","Date_Modif":null}},{"type":"Feature","id":56,"geometry":{"type":"Point","coordinates":[163.91517099984185,-74.622905999712088]},"properties":{"OBJECTID":56,"Record_ID_":51,"English_Na":"Browning Pass","Official_N":"Browning Pass","Operator__":"Italy","Operator_1":" ","Type":"Airfield Camp","Seasonalit":"Seasonal","Status":"Open","Year_Estab":1997,"Antarctic":"Transantarctic Mountains","Latitude__":-74.622906,"Longitude":163.91517099999999,"Latitude_1":"74° 37.3744' S","Longitud_1":"163° 54.9103' E","Elevation":"63","Elevatio_1":"MSL","Peak_Popul":2,"Photo_URL":" ","Webcam_URL":" ","Date_Modif":null}},{"type":"Feature","id":57,"geometry":{"type":"Point","coordinates":[123.33260500002075,-75.099974999746394]},"properties":{"OBJECTID":57,"Record_ID_":42,"English_Na":"Concordia","Official_N":"Concordia Station","Operator__":"Italy","Operator_1":"France","Type":"Station","Seasonalit":"Year-Round","Status":"Open","Year_Estab":1997,"Antarctic":"East Antarctica","Latitude__":-75.099975000000001,"Longitude":123.332605,"Latitude_1":"75° 5.9985' S","Longitud_1":"123° 19.9563' E","Elevation":"3,233","Elevatio_1":"MSL","Peak_Popul":70,"Photo_URL":"https://pgc.quickbase.com/up/bibrbwkpg/a/r42/e56/v0/Concordia_aerial_pnra_15-09-28.jpeg","Webcam_URL":"www.italiantartide.it","Date_Modif":1590969600000}},{"type":"Feature","id":58,"geometry":{"type":"Point","coordinates":[164.02771099966299,-74.719163999618843]},"properties":{"OBJECTID":58,"Record_ID_":52,"English_Na":"Enigma Lake","Official_N":"Enigma Lake","Operator__":"Italy","Operator_1":" ","Type":"Airfield Camp","Seasonalit":"Seasonal","Status":"Open","Year_Estab":2005,"Antarctic":"Transantarctic Mountains","Latitude__":-74.719164000000006,"Longitude":164.02771100000001,"Latitude_1":"74° 43.1498' S","Longitud_1":"164° 1.6627' E","Elevation":"250","Elevatio_1":"MSL","Peak_Popul":0,"Photo_URL":" ","Webcam_URL":" ","Date_Modif":null}},{"type":"Feature","id":59,"geometry":{"type":"Point","coordinates":[164.11326799981839,-74.694806999643276]},"properties":{"OBJECTID":59,"Record_ID_":55,"English_Na":"Mario Zucchelli","Official_N":"Stazione Mario Zucchelli","Operator__":"Italy","Operator_1":" ","Type":"Station","Seasonalit":"Seasonal","Status":"Open","Year_Estab":1986,"Antarctic":"Transantarctic Mountains","Latitude__":-74.694806999999997,"Longitude":164.11326800000001,"Latitude_1":"74° 41.6884' S","Longitud_1":"164° 6.7961' E","Elevation":"15","Elevatio_1":"MSL","Peak_Popul":102,"Photo_URL":"https://pgc.quickbase.com/up/bibrbwkpg/a/r55/e56/v0/MZS_aerial_Nicklen_2011-10-25.jpeg","Webcam_URL":" ","Date_Modif":1590969600000}},{"type":"Feature","id":60,"geometry":{"type":"Point","coordinates":[145.82039900011387,-75.541702999593724]},"properties":{"OBJECTID":60,"Record_ID_":53,"English_Na":"Mid Point","Official_N":"Mid Point","Operator__":"Italy","Operator_1":" ","Type":"Airfield Camp","Seasonalit":"Seasonal","Status":"Open","Year_Estab":1988,"Antarctic":"East Antarctica","Latitude__":-75.541702999999998,"Longitude":145.82039900000001,"Latitude_1":"75° 32.5022' S","Longitud_1":"145° 49.2239' E","Elevation":"2,520","Elevatio_1":"MSL","Peak_Popul":0,"Photo_URL":" ","Webcam_URL":" ","Date_Modif":null}},{"type":"Feature","id":61,"geometry":{"type":"Point","coordinates":[159.20043200043654,-72.830215000421902]},"properties":{"OBJECTID":61,"Record_ID_":112,"English_Na":"Talos Dome","Official_N":"Talos Dome","Operator__":"Italy","Operator_1":" ","Type":"Camp","Seasonalit":"Seasonal","Status":"Open","Year_Estab":0,"Antarctic":"East Antarctica","Latitude__":-72.830214999999995,"Longitude":159.20043200000001,"Latitude_1":"72° 49.8129' S","Longitud_1":"159° 12.0259' E","Elevation":" ","Elevatio_1":" ","Peak_Popul":0,"Photo_URL":" ","Webcam_URL":" ","Date_Modif":1493856000000}},{"type":"Feature","id":62,"geometry":{"type":"Point","coordinates":[24.112516209855244,-71.52627262967809]},"properties":{"OBJECTID":62,"Record_ID_":57,"English_Na":"Asuka","Official_N":"Asuka Station","Operator__":"Japan","Operator_1":" ","Type":"Station","Seasonalit":"Seasonal","Status":"Temporarily Closed","Year_Estab":1985,"Antarctic":"East Antarctica","Latitude__":-71.526272629999994,"Longitude":24.112516209999999,"Latitude_1":"71° 31.5764' S","Longitud_1":"24° 6.751' E","Elevation":"980.3","Elevatio_1":" ","Peak_Popul":0,"Photo_URL":"https://pgc.quickbase.com/up/bibrbwkpg/a/r57/e56/v0/ASUKA_ovrview_JARE28_87md%B4%C7%D1.jpg","Webcam_URL":" ","Date_Modif":null}},{"type":"Feature","id":63,"geometry":{"type":"Point","coordinates":[39.698770189592608,-77.317075239830388]},"properties":{"OBJECTID":63,"Record_ID_":58,"English_Na":"Dome Fuji","Official_N":"Dome Fuji Station","Operator__":"Japan","Operator_1":" ","Type":"Station","Seasonalit":"Seasonal","Status":"Temporarily Closed","Year_Estab":1995,"Antarctic":"Dronning Maud Land","Latitude__":-77.317075239999994,"Longitude":39.698770189999998,"Latitude_1":"77° 19.0245' S","Longitud_1":"39° 41.9262' E","Elevation":"3,810","Elevatio_1":"MSL","Peak_Popul":15,"Photo_URL":"https://pgc.quickbase.com/up/bibrbwkpg/a/r58/e56/v0/DmFUJI_huts_JARE%B4%C7%D1_yymmd%B4%C7%D1.jpg","Webcam_URL":" ","Date_Modif":1536537600000}},{"type":"Feature","id":64,"geometry":{"type":"Point","coordinates":[44.27781167976525,-70.699045599674662]},"properties":{"OBJECTID":64,"Record_ID_":59,"English_Na":"Mizuho","Official_N":"Mizuho Station","Operator__":"Japan","Operator_1":" ","Type":"Station","Seasonalit":"Seasonal","Status":"Temporarily Closed","Year_Estab":1970,"Antarctic":"East Antarctica","Latitude__":-70.699045600000005,"Longitude":44.277811679999999,"Latitude_1":"70° 41.9427' S","Longitud_1":"44° 16.6687' E","Elevation":"2,244.40","Elevatio_1":" ","Peak_Popul":0,"Photo_URL":"https://pgc.quickbase.com/up/bibrbwkpg/a/r59/e56/v0/MIZUHO%20corrugate_JARE11_1970.jpg","Webcam_URL":" ","Date_Modif":1591315200000}},{"type":"Feature","id":65,"geometry":{"type":"Point","coordinates":[40.092448999821556,-69.028076000207193]},"properties":{"OBJECTID":65,"Record_ID_":56,"English_Na":"S17 Camp","Official_N":"S17 Camp","Operator__":"Japan","Operator_1":" ","Type":"Camp","Seasonalit":"Seasonal","Status":"Open","Year_Estab":0,"Antarctic":"Dronning Maud Land","Latitude__":-69.028075999999999,"Longitude":40.092449000000002,"Latitude_1":"69° 1.6846' S","Longitud_1":"40° 5.5469' E","Elevation":"620","Elevatio_1":" ","Peak_Popul":0,"Photo_URL":" ","Webcam_URL":" ","Date_Modif":1536537600000}},{"type":"Feature","id":66,"geometry":{"type":"Point","coordinates":[39.581835999731652,-69.004121999930305]},"properties":{"OBJECTID":66,"Record_ID_":60,"English_Na":"Syowa","Official_N":"Syowa Station","Operator__":"Japan","Operator_1":" ","Type":"Station","Seasonalit":"Year-Round","Status":"Open","Year_Estab":1957,"Antarctic":"Dronning Maud Land","Latitude__":-69.004121999999995,"Longitude":39.581836000000003,"Latitude_1":"69° 0.2473' S","Longitud_1":"39° 34.9102' E","Elevation":"29","Elevatio_1":"MSL","Peak_Popul":170,"Photo_URL":"https://pgc.quickbase.com/up/bibrbwkpg/a/r60/e56/v0/Syowa%20Station.jpg","Webcam_URL":"http://www.nipr.ac.jp/webcam-top.html","Date_Modif":null}},{"type":"Feature","id":67,"geometry":{"type":"Point","coordinates":[-68.124376999598837,-67.568636000351091]},"properties":{"OBJECTID":67,"Record_ID_":107,"English_Na":"Dirck Gerritsz Laboratory","Official_N":"Dirck Gerritsz Laboratory","Operator__":"Netherlands","Operator_1":"United Kingdom","Type":"Laboratory","Seasonalit":"Seasonal","Status":"Open","Year_Estab":2012,"Antarctic":"Antarctic Peninsula","Latitude__":-67.568635999999998,"Longitude":-68.124376999999996,"Latitude_1":"67° 34.1182' S","Longitud_1":"68° 7.4626' W","Elevation":"16","Elevatio_1":"MSL","Peak_Popul":10,"Photo_URL":"https://pgc.quickbase.com/up/bibrbwkpg/a/r107/e56/v0/Gerritsz_Lab_Vanderkroef_Jan2013.JPG","Webcam_URL":" ","Date_Modif":null}},{"type":"Feature","id":68,"geometry":{"type":"Point","coordinates":[166.76728099971842,-77.849437000017474]},"properties":{"OBJECTID":68,"Record_ID_":61,"English_Na":"Scott Base","Official_N":"Scott Base Station","Operator__":"New Zealand","Operator_1":" ","Type":"Station","Seasonalit":"Year-Round","Status":"Open","Year_Estab":1957,"Antarctic":"Transantarctic Mountains","Latitude__":-77.849436999999995,"Longitude":166.767281,"Latitude_1":"77° 50.9662' S","Longitud_1":"166° 46.0369' E","Elevation":"10","Elevatio_1":" ","Peak_Popul":86,"Photo_URL":"https://pgc.quickbase.com/up/bibrbwkpg/a/r61/e56/v0/Scott%20Base.jpg","Webcam_URL":"https://www.antarcticanz.govt.nz/scott-base/webcams-weather","Date_Modif":null}},{"type":"Feature","id":69,"geometry":{"type":"Point","coordinates":[5.1598929999620395,-71.889515000416907]},"properties":{"OBJECTID":69,"Record_ID_":62,"English_Na":"Tor","Official_N":"Tor","Operator__":"Norway","Operator_1":" ","Type":"Refuge","Seasonalit":"Seasonal","Status":"Open","Year_Estab":1993,"Antarctic":"East Antarctica","Latitude__":-71.889515000000003,"Longitude":5.1598930000000003,"Latitude_1":"71° 53.3709' S","Longitud_1":"5° 9.5936' E","Elevation":"1,625","Elevatio_1":"WGS84","Peak_Popul":6,"Photo_URL":"https://pgc.quickbase.com/up/bibrbwkpg/a/r62/e56/v0/Tor%20Station%202018%20Seb%20Descamps.jpg","Webcam_URL":" ","Date_Modif":null}},{"type":"Feature","id":70,"geometry":{"type":"Point","coordinates":[2.533070000280361,-72.011946000407534]},"properties":{"OBJECTID":70,"Record_ID_":63,"English_Na":"Troll","Official_N":"Troll","Operator__":"Norway","Operator_1":" ","Type":"Station","Seasonalit":"Year-Round","Status":"Open","Year_Estab":1990,"Antarctic":"Dronning Maud Land","Latitude__":-72.011945999999995,"Longitude":2.5330699999999999,"Latitude_1":"72° 0.7168' S","Longitud_1":"2° 31.9842' E","Elevation":"1,275","Elevatio_1":"WGS84","Peak_Popul":70,"Photo_URL":"https://pgc.quickbase.com/up/bibrbwkpg/a/r63/e56/v0/Troll%202019%20Sven%20Lidstrom.jpg","Webcam_URL":"http://www.npolar.no/en/about-us/stations-vessels/troll/","Date_Modif":null}},{"type":"Feature","id":71,"geometry":{"type":"Point","coordinates":[-58.47055895972818,-62.091592519579081]},"properties":{"OBJECTID":71,"Record_ID_":64,"English_Na":"Machu Picchu","Official_N":"Machu Picchu Station","Operator__":"Peru","Operator_1":" ","Type":"Station","Seasonalit":"Seasonal","Status":"Open","Year_Estab":1989,"Antarctic":"Antarctic Peninsula","Latitude__":-62.091592519999999,"Longitude":-58.470558959999998,"Latitude_1":"62° 5.4956' S","Longitud_1":"58° 28.2335' W","Elevation":"3.5","Elevatio_1":"MSL","Peak_Popul":30,"Photo_URL":"https://pgc.quickbase.com/up/bibrbwkpg/a/r64/e56/v0/Machu%20Pichu%20Station_Peruvian%20National%20Antarctic%20Program.jpg","Webcam_URL":" ","Date_Modif":1591315200000}},{"type":"Feature","id":72,"geometry":{"type":"Point","coordinates":[-58.473321999910354,-62.159772999923973]},"properties":{"OBJECTID":72,"Record_ID_":65,"English_Na":"Henryk Arctowski","Official_N":"Henryk Arctowski Polish Antarctic Station","Operator__":"Poland","Operator_1":" ","Type":"Station","Seasonalit":"Year-Round","Status":"Open","Year_Estab":1977,"Antarctic":"Antarctic Peninsula","Latitude__":-62.159773000000001,"Longitude":-58.473322000000003,"Latitude_1":"62° 9.5864' S","Longitud_1":"58° 28.3993' W","Elevation":"2","Elevatio_1":"WGS84","Peak_Popul":40,"Photo_URL":"https://pgc.quickbase.com/up/bibrbwkpg/a/r65/e56/v0/arctowski_overlook_latusek_280116.JPG","Webcam_URL":" ","Date_Modif":null}},{"type":"Feature","id":73,"geometry":{"type":"Point","coordinates":[46.153333000417661,-67.658332999868037]},"properties":{"OBJECTID":73,"Record_ID_":101,"English_Na":"Mountain Evening","Official_N":"Mountain Vechernyaya","Operator__":"Republic of Belarus","Operator_1":" ","Type":"Station","Seasonalit":"Seasonal","Status":"Open","Year_Estab":2006,"Antarctic":"East Antarctica","Latitude__":-67.658332999999999,"Longitude":46.153333000000003,"Latitude_1":"67° 39.5' S","Longitud_1":"46° 9.2' E","Elevation":"95","Elevatio_1":"MSL","Peak_Popul":12,"Photo_URL":"https://pgc.quickbase.com/up/bibrbwkpg/a/r101/e56/v0/Geographical%20complex%20Mountain%20Vechernua_First%20building%20Belarus%20Antarctic%20station%20_Torbic_16.01.21.jpg","Webcam_URL":" ","Date_Modif":1606780800000}},{"type":"Feature","id":74,"geometry":{"type":"Point","coordinates":[164.23584999957791,-74.627363000202251]},"properties":{"OBJECTID":74,"Record_ID_":106,"English_Na":"Jang Bogo","Official_N":"Jang Bogo","Operator__":"Republic of Korea","Operator_1":" ","Type":"Station","Seasonalit":"Year-Round","Status":"Open","Year_Estab":2014,"Antarctic":"Transantarctic Mountains","Latitude__":-74.627363000000003,"Longitude":164.23585,"Latitude_1":"74° 37.6418' S","Longitud_1":"164° 14.151' E","Elevation":"36.6","Elevatio_1":"MSL","Peak_Popul":80,"Photo_URL":"https://pgc.quickbase.com/up/bibrbwkpg/a/r106/e56/v0/JangBogo%20landscape_KOPRI_Mar2014.JPG","Webcam_URL":"https://monitor.kopri.re.kr/cctv/view.html?base=jangbogo","Date_Modif":1591315200000}},{"type":"Feature","id":75,"geometry":{"type":"Point","coordinates":[-58.786504000159425,-62.223239000279591]},"properties":{"OBJECTID":75,"Record_ID_":105,"English_Na":"King Sejong","Official_N":"King Sejong","Operator__":"Republic of Korea","Operator_1":" ","Type":"Station","Seasonalit":"Year-Round","Status":"Open","Year_Estab":1988,"Antarctic":"Antarctic Peninsula","Latitude__":-62.223239,"Longitude":-58.786504000000001,"Latitude_1":"62° 13.3943' S","Longitud_1":"58° 47.1902' W","Elevation":"10","Elevatio_1":"MSL","Peak_Popul":78,"Photo_URL":"https://pgc.quickbase.com/up/bibrbwkpg/a/r105/e56/v0/KSJ_201803.jpg","Webcam_URL":"https://monitor.kopri.re.kr/cctv/view.html?base=sejong","Date_Modif":null}},{"type":"Feature","id":76,"geometry":{"type":"Point","coordinates":[-58.960608999905389,-62.19818399959189]},"properties":{"OBJECTID":76,"Record_ID_":68,"English_Na":"Bellingshausen","Official_N":"Bellingshausen","Operator__":"Russia","Operator_1":" ","Type":"Station","Seasonalit":"Year-Round","Status":"Open","Year_Estab":1968,"Antarctic":"Antarctic Peninsula","Latitude__":-62.198183999999998,"Longitude":-58.960608999999998,"Latitude_1":"62° 11.891' S","Longitud_1":"58° 57.6365' W","Elevation":"16","Elevatio_1":"MSL","Peak_Popul":40,"Photo_URL":"https://pgc.quickbase.com/up/bibrbwkpg/a/r68/e56/v0/Bellingshausen01%20.jpg","Webcam_URL":" ","Date_Modif":null}},{"type":"Feature","id":77,"geometry":{"type":"Point","coordinates":[100.73333299961831,-66.266667000281814]},"properties":{"OBJECTID":77,"Record_ID_":108,"English_Na":"Bunger Oasis","Official_N":"Bunger Oasis","Operator__":"Russia","Operator_1":" ","Type":"Station","Seasonalit":"Seasonal","Status":"Open","Year_Estab":0,"Antarctic":"East Antarctica","Latitude__":-66.266666999999998,"Longitude":100.733333,"Latitude_1":"66° 16' S","Longitud_1":"100° 44' E","Elevation":"29","Elevatio_1":" ","Peak_Popul":10,"Photo_URL":" ","Webcam_URL":" ","Date_Modif":null}},{"type":"Feature","id":78,"geometry":{"type":"Point","coordinates":[73.709213999826261,-69.747827000415725]},"properties":{"OBJECTID":78,"Record_ID_":69,"English_Na":"Druzhnaya IV","Official_N":"Druzhnaya IV","Operator__":"Russia","Operator_1":" ","Type":"Station","Seasonalit":"Seasonal","Status":"Open","Year_Estab":1987,"Antarctic":"East Antarctica","Latitude__":-69.747827000000001,"Longitude":73.709214000000003,"Latitude_1":"69° 44.8696' S","Longitud_1":"73° 42.5528' E","Elevation":"20","Elevatio_1":"MSL","Peak_Popul":50,"Photo_URL":"https://pgc.quickbase.com/up/bibrbwkpg/a/r69/e56/v0/Druzhnaya%20IV_AARI-RAE_2006.jpg","Webcam_URL":" ","Date_Modif":1591315200000}},{"type":"Feature","id":79,"geometry":{"type":"Point","coordinates":[159.39114799998026,-69.501496000140264]},"properties":{"OBJECTID":79,"Record_ID_":70,"English_Na":"Leningradskaya","Official_N":"Leningradskaya","Operator__":"Russia","Operator_1":" ","Type":"Station","Seasonalit":"Seasonal","Status":"Temporarily Closed","Year_Estab":1971,"Antarctic":"East Antarctica","Latitude__":-69.501496000000003,"Longitude":159.39114799999999,"Latitude_1":"69° 30.0898' S","Longitud_1":"159° 23.4689' E","Elevation":"300","Elevatio_1":"MSL","Peak_Popul":10,"Photo_URL":"https://pgc.quickbase.com/up/bibrbwkpg/a/r70/e56/v0/Leningradskaya_AARI-RAE_2014.jpg","Webcam_URL":" ","Date_Modif":1591315200000}},{"type":"Feature","id":80,"geometry":{"type":"Point","coordinates":[93.009558999648164,-66.553181000103052]},"properties":{"OBJECTID":80,"Record_ID_":71,"English_Na":"Mirny","Official_N":"Mirny","Operator__":"Russia","Operator_1":" ","Type":"Station","Seasonalit":"Year-Round","Status":"Open","Year_Estab":1956,"Antarctic":"East Antarctica","Latitude__":-66.553180999999995,"Longitude":93.009558999999996,"Latitude_1":"66° 33.1909' S","Longitud_1":"93° 0.5735' E","Elevation":"35","Elevatio_1":"MSL","Peak_Popul":50,"Photo_URL":"https://pgc.quickbase.com/up/bibrbwkpg/a/r71/e56/v0/Mirny01.jpg","Webcam_URL":" ","Date_Modif":null}},{"type":"Feature","id":81,"geometry":{"type":"Point","coordinates":[45.842037999953789,-67.665443000394134]},"properties":{"OBJECTID":81,"Record_ID_":72,"English_Na":"Molodezhnaya","Official_N":"Molodezhnaya","Operator__":"Russia","Operator_1":" ","Type":"Station","Seasonalit":"Seasonal","Status":"Open","Year_Estab":1963,"Antarctic":"East Antarctica","Latitude__":-67.665442999999996,"Longitude":45.842038000000002,"Latitude_1":"67° 39.9266' S","Longitud_1":"45° 50.5223' E","Elevation":"40","Elevatio_1":"MSL","Peak_Popul":15,"Photo_URL":"https://pgc.quickbase.com/up/bibrbwkpg/a/r72/e56/v0/Molodezhnaya_AARI-RAE_2014.jpg","Webcam_URL":" ","Date_Modif":1591315200000}},{"type":"Feature","id":82,"geometry":{"type":"Point","coordinates":[11.832150999569023,-70.775796000385071]},"properties":{"OBJECTID":82,"Record_ID_":76,"English_Na":"Novolazarevskaya","Official_N":"Novolazarevskaya","Operator__":"Russia","Operator_1":" ","Type":"Station","Seasonalit":"Year-Round","Status":"Open","Year_Estab":1961,"Antarctic":"Dronning Maud Land","Latitude__":-70.775796,"Longitude":11.832151,"Latitude_1":"70° 46.5478' S","Longitud_1":"11° 49.9291' E","Elevation":"102","Elevatio_1":"MSL","Peak_Popul":70,"Photo_URL":"https://pgc.quickbase.com/up/bibrbwkpg/a/r76/e56/v0/Novolazarevskaya01.jpg","Webcam_URL":" ","Date_Modif":null}},{"type":"Feature","id":83,"geometry":{"type":"Point","coordinates":[76.388246999699334,-69.377949999992438]},"properties":{"OBJECTID":83,"Record_ID_":77,"English_Na":"Progress","Official_N":"Progress","Operator__":"Russia","Operator_1":" ","Type":"Station","Seasonalit":"Year-Round","Status":"Open","Year_Estab":1989,"Antarctic":"East Antarctica","Latitude__":-69.377949999999998,"Longitude":76.388247000000007,"Latitude_1":"69° 22.677' S","Longitud_1":"76° 23.2948' E","Elevation":"15","Elevatio_1":"MSL","Peak_Popul":50,"Photo_URL":"https://pgc.quickbase.com/up/bibrbwkpg/a/r77/e56/v0/Progress.jpg","Webcam_URL":" ","Date_Modif":1549670400000}},{"type":"Feature","id":84,"geometry":{"type":"Point","coordinates":[76.403538999825059,-69.412275000091142]},"properties":{"OBJECTID":84,"Record_ID_":109,"English_Na":"Progress 3","Official_N":"Progress 3","Operator__":"Russia","Operator_1":" ","Type":"Station","Seasonalit":"Seasonal","Status":"Open","Year_Estab":0,"Antarctic":"East Antarctica","Latitude__":-69.412274999999994,"Longitude":76.403538999999995,"Latitude_1":"69° 24.7365' S","Longitud_1":"76° 24.2123' E","Elevation":"105","Elevatio_1":" ","Peak_Popul":0,"Photo_URL":" ","Webcam_URL":" ","Date_Modif":1549670400000}},{"type":"Feature","id":85,"geometry":{"type":"Point","coordinates":[-136.80007199962307,-74.765726000154757]},"properties":{"OBJECTID":85,"Record_ID_":78,"English_Na":"Russkaya","Official_N":"Russkaya","Operator__":"Russia","Operator_1":" ","Type":"Station","Seasonalit":"Seasonal","Status":"Temporarily Closed","Year_Estab":1980,"Antarctic":"West Antarctica","Latitude__":-74.765726000000001,"Longitude":-136.800072,"Latitude_1":"74° 45.9436' S","Longitud_1":"136° 48.0043' W","Elevation":"126","Elevatio_1":"MSL","Peak_Popul":10,"Photo_URL":"https://pgc.quickbase.com/up/bibrbwkpg/a/r78/e56/v0/Russkaya_AARI-RAE_2014.jpg","Webcam_URL":" ","Date_Modif":1591315200000}},{"type":"Feature","id":86,"geometry":{"type":"Point","coordinates":[68.794936999642857,-70.576576999928591]},"properties":{"OBJECTID":86,"Record_ID_":79,"English_Na":"Soyuz","Official_N":"Soyuz","Operator__":"Russia","Operator_1":" ","Type":"Station","Seasonalit":"Seasonal","Status":"Temporarily Closed","Year_Estab":1982,"Antarctic":"East Antarctica","Latitude__":-70.576577,"Longitude":68.794937000000004,"Latitude_1":"70° 34.5946' S","Longitud_1":"68° 47.6962' E","Elevation":"336","Elevatio_1":"MSL","Peak_Popul":30,"Photo_URL":" ","Webcam_URL":" ","Date_Modif":1538956800000}},{"type":"Feature","id":87,"geometry":{"type":"Point","coordinates":[106.83688200000438,-78.464181999799393]},"properties":{"OBJECTID":87,"Record_ID_":80,"English_Na":"Vostok","Official_N":"Vostok","Operator__":"Russia","Operator_1":" ","Type":"Station","Seasonalit":"Year-Round","Status":"Open","Year_Estab":1957,"Antarctic":"East Antarctica","Latitude__":-78.464181999999994,"Longitude":106.836882,"Latitude_1":"78° 27.8509' S","Longitud_1":"106° 50.2129' E","Elevation":"3,488","Elevatio_1":"MSL","Peak_Popul":30,"Photo_URL":"https://pgc.quickbase.com/up/bibrbwkpg/a/r80/e56/v0/Vostok01.jpg","Webcam_URL":" ","Date_Modif":1538956800000}},{"type":"Feature","id":88,"geometry":{"type":"Point","coordinates":[-2.8403240003522683,-71.672872999589231]},"properties":{"OBJECTID":88,"Record_ID_":81,"English_Na":"SANAE IV","Official_N":"SANAE IV","Operator__":"South Africa","Operator_1":" ","Type":"Station","Seasonalit":"Year-Round","Status":"Open","Year_Estab":1962,"Antarctic":"Dronning Maud Land","Latitude__":-71.672872999999996,"Longitude":-2.8403239999999998,"Latitude_1":"71° 40.3724' S","Longitud_1":"2° 50.4194' W","Elevation":"850","Elevatio_1":"MSL","Peak_Popul":80,"Photo_URL":"https://pgc.quickbase.com/up/bibrbwkpg/a/r81/e56/v0/SANAE%20BASE.jpg","Webcam_URL":" ","Date_Modif":null}},{"type":"Feature","id":89,"geometry":{"type":"Point","coordinates":[-8.2499989995541227,-70.64999739996]},"properties":{"OBJECTID":89,"Record_ID_":232,"English_Na":"SANAP Summer Station","Official_N":"SANAP Summer Station","Operator__":"South Africa","Operator_1":" ","Type":"Station","Seasonalit":"Seasonal","Status":"Open","Year_Estab":2010,"Antarctic":" ","Latitude__":-70.649997400000004,"Longitude":-8.2499990000000007,"Latitude_1":"70° 38.9998' S","Longitud_1":"8° 14.9999' W","Elevation":" ","Elevatio_1":" ","Peak_Popul":20,"Photo_URL":" ","Webcam_URL":" ","Date_Modif":null}},{"type":"Feature","id":90,"geometry":{"type":"Point","coordinates":[-60.675745449892531,-62.977196559873278]},"properties":{"OBJECTID":90,"Record_ID_":82,"English_Na":"Gabriel de Castilla","Official_N":"Gabriel de Castilla","Operator__":"Spain","Operator_1":" ","Type":"Station","Seasonalit":"Seasonal","Status":"Open","Year_Estab":1990,"Antarctic":"Antarctic Peninsula","Latitude__":-62.977196560000003,"Longitude":-60.675745450000001,"Latitude_1":"62° 58.6318' S","Longitud_1":"60° 40.5447' W","Elevation":"15","Elevatio_1":"MSL","Peak_Popul":36,"Photo_URL":"https://pgc.quickbase.com/up/bibrbwkpg/a/r82/e56/v0/Gabriel%20de%20Castilla_station_aerial_view_2_Gabriel%20Gollanes_15_12_22.jpg","Webcam_URL":" ","Date_Modif":1570579200000}},{"type":"Feature","id":91,"geometry":{"type":"Point","coordinates":[-61.099436000171238,-62.663771999877838]},"properties":{"OBJECTID":91,"Record_ID_":110,"English_Na":"International Field Camp Peninsula Byers","Official_N":"International Field Camp Peninsula Byers","Operator__":"Spain","Operator_1":" ","Type":"Camp","Seasonalit":"Seasonal","Status":"Open","Year_Estab":2001,"Antarctic":"Antarctic Peninsula","Latitude__":-62.663772000000002,"Longitude":-61.099435999999997,"Latitude_1":"62° 39.8263' S","Longitud_1":"61° 5.9662' W","Elevation":"10","Elevatio_1":"MSL","Peak_Popul":12,"Photo_URL":"https://pgc.quickbase.com/up/bibrbwkpg/a/r110/e56/v0/Byers_camp_overview_UTM.JPG","Webcam_URL":" ","Date_Modif":1541462400000}},{"type":"Feature","id":92,"geometry":{"type":"Point","coordinates":[-60.38814603041493,-62.663408629704463]},"properties":{"OBJECTID":92,"Record_ID_":83,"English_Na":"Juan Carlos I","Official_N":"Juan Carlos I Station","Operator__":"Spain","Operator_1":" ","Type":"Station","Seasonalit":"Seasonal","Status":"Open","Year_Estab":1988,"Antarctic":"Antarctic Peninsula","Latitude__":-62.663408629999999,"Longitude":-60.388146030000001,"Latitude_1":"62° 39.8045' S","Longitud_1":"60° 23.2888' W","Elevation":"12","Elevatio_1":"MSL","Peak_Popul":50,"Photo_URL":"https://pgc.quickbase.com/up/bibrbwkpg/a/r83/e56/v0/JuanCarlosI_station_Felipe_14_11_30.JPG","Webcam_URL":" ","Date_Modif":1570579200000}},{"type":"Feature","id":93,"geometry":{"type":"Point","coordinates":[-11.224872000342486,-74.576060999615379]},"properties":{"OBJECTID":93,"Record_ID_":84,"English_Na":"Svea","Official_N":"Svea","Operator__":"Sweden","Operator_1":" ","Type":"Refuge","Seasonalit":"Seasonal","Status":"Temporarily Closed","Year_Estab":0,"Antarctic":"East Antarctica","Latitude__":-74.576060999999996,"Longitude":-11.224872,"Latitude_1":"74° 34.5637' S","Longitud_1":"11° 13.4923' W","Elevation":" ","Elevatio_1":" ","Peak_Popul":0,"Photo_URL":" ","Webcam_URL":" ","Date_Modif":null}},{"type":"Feature","id":94,"geometry":{"type":"Point","coordinates":[-13.41291000009636,-73.04279900027359]},"properties":{"OBJECTID":94,"Record_ID_":85,"English_Na":"Wasa","Official_N":"Wasa","Operator__":"Sweden","Operator_1":" ","Type":"Station","Seasonalit":"Seasonal","Status":"Open","Year_Estab":1989,"Antarctic":"Dronning Maud Land","Latitude__":-73.042799000000002,"Longitude":-13.41291,"Latitude_1":"73° 2.5679' S","Longitud_1":"13° 24.7746' W","Elevation":"440","Elevatio_1":"WGS84","Peak_Popul":10,"Photo_URL":"https://pgc.quickbase.com/up/bibrbwkpg/a/r85/e56/v0/Wasa%20station%20Sweden.jpg","Webcam_URL":" ","Date_Modif":null}},{"type":"Feature","id":95,"geometry":{"type":"Point","coordinates":[-67.237747000123932,-67.8296499996477]},"properties":{"OBJECTID":95,"Record_ID_":237,"English_Na":" Turkish Scientific Research Camp","Official_N":" Turkish Scientific Research Camp","Operator__":"Turkey","Operator_1":" ","Type":"Camp","Seasonalit":"Seasonal","Status":"Open","Year_Estab":2019,"Antarctic":"Antarctic Peninsula","Latitude__":-67.829650000000001,"Longitude":-67.237746999999999,"Latitude_1":"67° 49.779' S","Longitud_1":"67° 14.2648' W","Elevation":"4","Elevatio_1":" ","Peak_Popul":8,"Photo_URL":"https://pgc.quickbase.com/up/bibrbwkpg/a/r237/e56/v0/Turkish_Sci_Res_Camp_2020.jpeg","Webcam_URL":" ","Date_Modif":null}},{"type":"Feature","id":96,"geometry":{"type":"Point","coordinates":[-64.257481229974758,-65.245742950176975]},"properties":{"OBJECTID":96,"Record_ID_":86,"English_Na":"Vernadsky","Official_N":"Vernadsky","Operator__":"Ukraine","Operator_1":" ","Type":"Station","Seasonalit":"Year-Round","Status":"Open","Year_Estab":1996,"Antarctic":"Antarctic Peninsula","Latitude__":-65.245742949999993,"Longitude":-64.257481229999996,"Latitude_1":"65° 14.7446' S","Longitud_1":"64° 15.4489' W","Elevation":"7","Elevatio_1":"MSL","Peak_Popul":24,"Photo_URL":"https://pgc.quickbase.com/up/bibrbwkpg/a/r86/e56/v0/Vernadsky_general_view_Pishniak_2012.JPG","Webcam_URL":" ","Date_Modif":null}},{"type":"Feature","id":97,"geometry":{"type":"Point","coordinates":[-68.289064000303313,-71.32341199996381]},"properties":{"OBJECTID":97,"Record_ID_":87,"English_Na":"Fossil Bluff","Official_N":"Fossil Bluff","Operator__":"United Kingdom","Operator_1":" ","Type":"Depot","Seasonalit":"Seasonal","Status":"Open","Year_Estab":1961,"Antarctic":"Antarctic Peninsula","Latitude__":-71.323412000000005,"Longitude":-68.289063999999996,"Latitude_1":"71° 19.4047' S","Longitud_1":"68° 17.3438' W","Elevation":"92","Elevatio_1":"WGS84","Peak_Popul":6,"Photo_URL":" ","Webcam_URL":" ","Date_Modif":1575849600000}},{"type":"Feature","id":98,"geometry":{"type":"Point","coordinates":[-25.473889000277097,-75.571110999572909]},"properties":{"OBJECTID":98,"Record_ID_":90,"English_Na":"Halley VI","Official_N":"Halley VI","Operator__":"United Kingdom","Operator_1":" ","Type":"Station","Seasonalit":"Seasonal","Status":"Open","Year_Estab":1956,"Antarctic":"Dronning Maud Land","Latitude__":-75.571111000000002,"Longitude":-25.473889,"Latitude_1":"75° 34.2667' S","Longitud_1":"25° 28.4333' W","Elevation":"37","Elevatio_1":"WGS84","Peak_Popul":0,"Photo_URL":"https://pgc.quickbase.com/up/bibrbwkpg/a/r90/e56/v0/BAS-10011257.jpg","Webcam_URL":"https://www.bas.ac.uk/polar-operations/sites-and-facilities/facility/halley/","Date_Modif":null}},{"type":"Feature","id":99,"geometry":{"type":"Point","coordinates":[-68.124887999781322,-67.569529000163186]},"properties":{"OBJECTID":99,"Record_ID_":91,"English_Na":"Rothera","Official_N":"Rothera Research Station","Operator__":"United Kingdom","Operator_1":" ","Type":"Station","Seasonalit":"Year-Round","Status":"Open","Year_Estab":1975,"Antarctic":"Antarctic Peninsula","Latitude__":-67.569529000000003,"Longitude":-68.124887999999999,"Latitude_1":"67° 34.1717' S","Longitud_1":"68° 7.4933' W","Elevation":"16","Elevatio_1":"WGS84","Peak_Popul":136,"Photo_URL":"https://pgc.quickbase.com/up/bibrbwkpg/a/r91/e56/v0/Rothera%20Station_BAS.jpg","Webcam_URL":"https://www.bas.ac.uk/polar-operations/sites-and-facilities/facility/rothera/","Date_Modif":1588636800000}},{"type":"Feature","id":100,"geometry":{"type":"Point","coordinates":[-45.595389160181583,-60.708287390250803]},"properties":{"OBJECTID":100,"Record_ID_":92,"English_Na":"Signy","Official_N":"Signy Station","Operator__":"United Kingdom","Operator_1":" ","Type":"Station","Seasonalit":"Seasonal","Status":"Open","Year_Estab":1947,"Antarctic":" ","Latitude__":-60.708287390000002,"Longitude":-45.595389160000003,"Latitude_1":"60° 42.4972' S","Longitud_1":"45° 35.7233' W","Elevation":"5","Elevatio_1":"WGS84","Peak_Popul":8,"Photo_URL":"https://pgc.quickbase.com/up/bibrbwkpg/a/r92/e56/v0/Signy_HRES.jpg","Webcam_URL":" ","Date_Modif":1591315200000}},{"type":"Feature","id":101,"geometry":{"type":"Point","coordinates":[-71.585199999880047,-74.856351000198458]},"properties":{"OBJECTID":101,"Record_ID_":89,"English_Na":"Sky Blu","Official_N":"Sky Blu","Operator__":"United Kingdom","Operator_1":" ","Type":"Depot","Seasonalit":"Seasonal","Status":"Open","Year_Estab":0,"Antarctic":"Antarctic Peninsula","Latitude__":-74.856351000000004,"Longitude":-71.5852,"Latitude_1":"74° 51.3811' S","Longitud_1":"71° 35.112' W","Elevation":"1,400","Elevatio_1":"WGS84","Peak_Popul":6,"Photo_URL":" ","Webcam_URL":" ","Date_Modif":1575849600000}},{"type":"Feature","id":102,"geometry":{"type":"Point","coordinates":[-63.499999999800139,-64.81666699958231]},"properties":{"OBJECTID":102,"Record_ID_":235,"English_Na":"Port Lockroy","Official_N":"Port Lockroy","Operator__":"United Kingdom Heritage Trust","Operator_1":" ","Type":"Station","Seasonalit":"Seasonal","Status":"Open","Year_Estab":0,"Antarctic":" ","Latitude__":-64.816666999999995,"Longitude":-63.5,"Latitude_1":"64° 49' S","Longitud_1":"63° 30' W","Elevation":" ","Elevatio_1":" ","Peak_Popul":0,"Photo_URL":"https://pgc.quickbase.com/up/bibrbwkpg/a/r235/e56/v0/Port%20Lockroy.jpg","Webcam_URL":" ","Date_Modif":1591315200000}},{"type":"Feature","id":103,"geometry":{"type":"Point","coordinates":[139.27279999982022,-89.997499999725164]},"properties":{"OBJECTID":103,"Record_ID_":2,"English_Na":"Amundsen-Scott South Pole","Official_N":"Amundsen-Scott South Pole Station","Operator__":"United States","Operator_1":" ","Type":"Station","Seasonalit":"Year-Round","Status":"Open","Year_Estab":1957,"Antarctic":"East Antarctica","Latitude__":-89.997500000000002,"Longitude":139.27279999999999,"Latitude_1":"89° 59.85' S","Longitud_1":"139° 16.368' E","Elevation":"2,830","Elevatio_1":"WGS84","Peak_Popul":153,"Photo_URL":"https://pgc.quickbase.com/up/bibrbwkpg/a/r2/e56/v0/south-pole-station.jpg","Webcam_URL":"https://www.usap.gov/videoClipsAndMaps/spwebcam.cfm","Date_Modif":null}},{"type":"Feature","id":104,"geometry":{"type":"Point","coordinates":[-119.56135300034066,-80.013893999608342]},"properties":{"OBJECTID":104,"Record_ID_":99,"English_Na":"Byrd Surface","Official_N":"Byrd Surface Camp","Operator__":"United States","Operator_1":" ","Type":"Camp","Seasonalit":"Seasonal","Status":"Open","Year_Estab":0,"Antarctic":"West Antarctica","Latitude__":-80.013893999999993,"Longitude":-119.561353,"Latitude_1":"80° 0.8336' S","Longitud_1":"119° 33.6812' W","Elevation":" ","Elevatio_1":" ","Peak_Popul":0,"Photo_URL":" ","Webcam_URL":" ","Date_Modif":null}},{"type":"Feature","id":105,"geometry":{"type":"Point","coordinates":[163.67916600001092,-77.413665999686089]},"properties":{"OBJECTID":105,"Record_ID_":95,"English_Na":"Marble Point Refueling Facility","Official_N":"Marble Point Refueling Facility","Operator__":"United States","Operator_1":" ","Type":"Depot","Seasonalit":"Seasonal","Status":"Open","Year_Estab":0,"Antarctic":"Transantarctic Mountains","Latitude__":-77.413666000000006,"Longitude":163.67916600000001,"Latitude_1":"77° 24.82' S","Longitud_1":"163° 40.75' E","Elevation":" ","Elevatio_1":" ","Peak_Popul":0,"Photo_URL":" ","Webcam_URL":" ","Date_Modif":1486684800000}},{"type":"Feature","id":106,"geometry":{"type":"Point","coordinates":[166.66842200037513,-77.848209000045301]},"properties":{"OBJECTID":106,"Record_ID_":1,"English_Na":"McMurdo","Official_N":"McMurdo Station","Operator__":"United States","Operator_1":" ","Type":"Station","Seasonalit":"Year-Round","Status":"Open","Year_Estab":1956,"Antarctic":"Transantarctic Mountains","Latitude__":-77.848208999999997,"Longitude":166.66842199999999,"Latitude_1":"77° 50.8925' S","Longitud_1":"166° 40.1053' E","Elevation":"10","Elevatio_1":"MSL","Peak_Popul":0,"Photo_URL":"https://pgc.quickbase.com/up/bibrbwkpg/a/r1/e56/v0/MCMURDO8.JPG","Webcam_URL":"https://www.usap.gov/videoclipsandmaps/mcmwebcam.cfm","Date_Modif":null}},{"type":"Feature","id":107,"geometry":{"type":"Point","coordinates":[-64.053333520225749,-64.774261000045101]},"properties":{"OBJECTID":107,"Record_ID_":3,"English_Na":"Palmer","Official_N":"Palmer Station","Operator__":"United States","Operator_1":" ","Type":"Station","Seasonalit":"Year-Round","Status":"Open","Year_Estab":1965,"Antarctic":"Antarctic Peninsula","Latitude__":-64.774260999999996,"Longitude":-64.053333519999995,"Latitude_1":"64° 46.4557' S","Longitud_1":"64° 3.2' W","Elevation":"10","Elevatio_1":"MSL","Peak_Popul":46,"Photo_URL":"https://pgc.quickbase.com/up/bibrbwkpg/a/r3/e56/v0/Palmer_Station_Hood_14-10-09.jpg","Webcam_URL":"https://www.usap.gov/videoClipsAndMaps/palwebcam.cfm","Date_Modif":null}},{"type":"Feature","id":108,"geometry":{"type":"Point","coordinates":[-175.2894690002941,-85.086231999806898]},"properties":{"OBJECTID":108,"Record_ID_":113,"English_Na":"Shackleton Glacier Camp","Official_N":"Shackleton Glacier Camp","Operator__":"United States","Operator_1":" ","Type":"Camp","Seasonalit":"Seasonal","Status":"Open","Year_Estab":2015,"Antarctic":"Transantarctic Mountains","Latitude__":-85.086231999999995,"Longitude":-175.289469,"Latitude_1":"85° 5.1739' S","Longitud_1":"175° 17.3681' W","Elevation":" ","Elevatio_1":" ","Peak_Popul":20,"Photo_URL":"https://pgc.quickbase.com/up/bibrbwkpg/a/r113/e56/v0/Shackleton.jpg","Webcam_URL":" ","Date_Modif":1491609600000}},{"type":"Feature","id":109,"geometry":{"type":"Point","coordinates":[-149.00184600039256,-81.65377099983175]},"properties":{"OBJECTID":109,"Record_ID_":111,"English_Na":"Siple Dome","Official_N":"Siple Dome","Operator__":"United States","Operator_1":" ","Type":"Camp","Seasonalit":"Seasonal","Status":"Open","Year_Estab":1973,"Antarctic":"West Antarctica","Latitude__":-81.653771000000006,"Longitude":-149.001846,"Latitude_1":"81° 39.2263' S","Longitud_1":"149° 0.1108' W","Elevation":" ","Elevatio_1":" ","Peak_Popul":10,"Photo_URL":" ","Webcam_URL":" ","Date_Modif":1473379200000}},{"type":"Feature","id":110,"geometry":{"type":"Point","coordinates":[-112.07215399990713,-79.471285999848988]},"properties":{"OBJECTID":110,"Record_ID_":114,"English_Na":"WAIS Divide","Official_N":"WAIS Divide Camp","Operator__":"United States","Operator_1":" ","Type":"Camp","Seasonalit":"Seasonal","Status":"Open","Year_Estab":2005,"Antarctic":"West Antarctica","Latitude__":-79.471286000000006,"Longitude":-112.072154,"Latitude_1":"79° 28.2772' S","Longitud_1":"112° 4.3292' W","Elevation":" ","Elevatio_1":" ","Peak_Popul":40,"Photo_URL":"https://pgc.quickbase.com/up/bibrbwkpg/a/r114/e56/v0/WSD%20aerial%20camp%20labeled%2015-16.jpg","Webcam_URL":" ","Date_Modif":null}},{"type":"Feature","id":111,"geometry":{"type":"Point","coordinates":[-58.902441730401506,-62.184550709947246]},"properties":{"OBJECTID":111,"Record_ID_":93,"English_Na":"Artigas","Official_N":"Artigas Station","Operator__":"Uruguay","Operator_1":" ","Type":"Station","Seasonalit":"Year-Round","Status":"Open","Year_Estab":1984,"Antarctic":"Antarctic Peninsula","Latitude__":-62.184550710000003,"Longitude":-58.90244173,"Latitude_1":"62° 11.073' S","Longitud_1":"58° 54.1465' W","Elevation":"17","Elevatio_1":"MSL","Peak_Popul":60,"Photo_URL":"https://pgc.quickbase.com/up/bibrbwkpg/a/r93/e56/v0/3%20base.jpg","Webcam_URL":" ","Date_Modif":null}},{"type":"Feature","id":112,"geometry":{"type":"Point","coordinates":[-56.990906800308551,-63.402372110284603]},"properties":{"OBJECTID":112,"Record_ID_":94,"English_Na":"Ruperto Elichiribehety","Official_N":"Ruperto Elichiribehety Station","Operator__":"Uruguay","Operator_1":" ","Type":"Station","Seasonalit":"Seasonal","Status":"Open","Year_Estab":1997,"Antarctic":"Antarctic Peninsula","Latitude__":-63.402372110000002,"Longitude":-56.990906799999998,"Latitude_1":"63° 24.1423' S","Longitud_1":"56° 59.4544' W","Elevation":"2.8","Elevatio_1":"MSL","Peak_Popul":8,"Photo_URL":"https://pgc.quickbase.com/up/bibrbwkpg/a/r94/e56/v0/Ruperto%20Station%2C%20IAU.JPG","Webcam_URL":" ","Date_Modif":1591315200000}}]}